lvbdist/__init__.py
lvbdist/_lvbdist.cp37-win_amd64.pyd
lvbdist/lvbdist_back.c
lvbdist/lvbdistcalcs/prob_func.c
lvbdist/lvbdistcalcs/prob_func.h
linearly_varying_binomial_distribution-1.0.3.dist-info/LICENSE
linearly_varying_binomial_distribution-1.0.3.dist-info/METADATA
linearly_varying_binomial_distribution-1.0.3.dist-info/WHEEL
linearly_varying_binomial_distribution-1.0.3.dist-info/top_level.txt
linearly_varying_binomial_distribution-1.0.3.dist-info/RECORD
