Metadata-Version: 2.1
Name: linearly-varying-binomial-distribution
Version: 1.0.3
Summary: computes ununiform step-increasing probability problems
Home-page: https://github.com/cleoold/linearly_varying_binomial_distribution_calcs_Python
Author: cos
Author-email: cleoold@gmail.com
License: UNKNOWN
Platform: UNKNOWN
Classifier: Programming Language :: Python :: 3
Classifier: License :: OSI Approved :: MIT License
Classifier: Operating System :: OS Independent
